{
  "source": "NLT_Harmony_of_the_Four_Gospels.docx",
  "columns": [
    "num",
    "Event/Topic",
    "Matthew",
    "Mark",
    "Luke",
    "John"
  ],
  "rows": [
    {
      "num": 171,
      "Event/Topic": "Question About the Messiah",
      "Matthew": "22:41–46",
      "Mark": "12:35–37",
      "Luke": "20:41–44",
      "John": ""
    },
    {
      "num": 172,
      "Event/Topic": "Jesus Condemns the Religious Leaders",
      "Matthew": "23:1–39",
      "Mark": "12:38–40",
      "Luke": "20:45–47",
      "John": ""
    },
    {
      "num": 173,
      "Event/Topic": "Jesus Praises the Poor Widow",
      "Matthew": "",
      "Mark": "12:41–44",
      "Luke": "21:1–4",
      "John": ""
    },
    {
      "num": 174,
      "Event/Topic": "Jesus Predicts the Future",
      "Matthew": "24:1–51",
      "Mark": "13:1–37",
      "Luke": "21:5–36",
      "John": ""
    },
    {
      "num": 175,
      "Event/Topic": "The Parable of the Three Servants",
      "Matthew": "25:1–30",
      "Mark": "",
      "Luke": "",
      "John": ""
    },
    {
      "num": 176,
      "Event/Topic": "The Final Judgment",
      "Matthew": "25:31–46",
      "Mark": "",
      "Luke": "",
      "John": ""
    },
    {
      "num": 177,
      "Event/Topic": "Religious Leaders Continue Their Plot to Murder Jesus",
      "Matthew": "26:1–5",
      "Mark": "14:1–2",
      "Luke": "22:1–2",
      "John": ""
    },
    {
      "num": 178,
      "Event/Topic": "Judas Agrees to Betray Jesus",
      "Matthew": "26:14–16",
      "Mark": "14:10–11",
      "Luke": "22:3–6",
      "John": ""
    },
    {
      "num": 179,
      "Event/Topic": "Preparations for the Passover",
      "Matthew": "26:17–19",
      "Mark": "14:12–16",
      "Luke": "22:7–13",
      "John": ""
    },
    {
      "num": 180,
      "Event/Topic": "Jesus and the Disciples Eat the Passover Meal",
      "Matthew": "26:20",
      "Mark": "14:17",
      "Luke": "22:14–16",
      "John": ""
    },
    {
      "num": 181,
      "Event/Topic": "Jesus Predicts His Betrayal",
      "Matthew": "26:21–25",
      "Mark": "14:18–21",
      "Luke": "22:21–23",
      "John": ""
    },
    {
      "num": 182,
      "Event/Topic": "Jesus Institutes the Lord’s Supper",
      "Matthew": "26:26–30",
      "Mark": "14:22–26",
      "Luke": "22:17–20",
      "John": ""
    },
    {
      "num": 183,
      "Event/Topic": "Jesus Predicts Peter’s Denial",
      "Matthew": "26:31–35",
      "Mark": "14:27–31",
      "Luke": "22:31–34",
      "John": ""
    },
    {
      "num": 184,
      "Event/Topic": "Jesus Prays in the Garden",
      "Matthew": "26:36–46",
      "Mark": "14:32–42",
      "Luke": "22:39–46",
      "John": ""
    },
    {
      "num": 185,
      "Event/Topic": "Jesus Is Betrayed and Arrested",
      "Matthew": "26:47–56",
      "Mark": "14:43–52",
      "Luke": "22:47–53",
      "John": "18:1–12"
    },
    {
      "num": 186,
      "Event/Topic": "Jesus Is Taken to the High Priest",
      "Matthew": "26:57–58",
      "Mark": "14:53–54",
      "Luke": "22:54",
      "John": "18:13–16"
    },
    {
      "num": 187,
      "Event/Topic": "The Religious Leaders Condemn Jesus",
      "Matthew": "26:59–68",
      "Mark": "14:55–65",
      "Luke": "22:63–71",
      "John": ""
    },
    {
      "num": 188,
      "Event/Topic": "Peter Denies Knowing Jesus",
      "Matthew": "26:69–75",
      "Mark": "14:66–72",
      "Luke": "22:55–62",
      "John": "18:17–27"
    },
    {
      "num": 189,
      "Event/Topic": "Jesus Is Taken to Pilate",
      "Matthew": "27:1–2",
      "Mark": "15:1",
      "Luke": "23:1",
      "John": "18:28–32"
    },
    {
      "num": 190,
      "Event/Topic": "Judas Hangs Himself",
      "Matthew": "27:3–10",
      "Mark": "",
      "Luke": "",
      "John": ""
    },
    {
      "num": 191,
      "Event/Topic": "Jesus Stands Trial Before Pilate",
      "Matthew": "27:11–14",
      "Mark": "15:2–5",
      "Luke": "23:2–5",
      "John": "18:33–38"
    },
    {
      "num": 192,
      "Event/Topic": "Jesus Is Sent to Herod",
      "Matthew": "",
      "Mark": "",
      "Luke": "23:6–12",
      "John": ""
    },
    {
      "num": 193,
      "Event/Topic": "Jesus Is Sent Back to Pilate",
      "Matthew": "",
      "Mark": "",
      "Luke": "23:13–16",
      "John": ""
    },
    {
      "num": 194,
      "Event/Topic": "Pilate Hands Jesus Over to Be Crucified",
      "Matthew": "27:15–26",
      "Mark": "15:6–15",
      "Luke": "23:17–25",
      "John": "18:39–19:16"
    },
    {
      "num": 195,
      "Event/Topic": "Soldiers Mock Jesus",
      "Matthew": "27:27–31",
      "Mark": "15:16–20",
      "Luke": "",
      "John": "19:2–3"
    },
    {
      "num": 196,
      "Event/Topic": "Jesus Is Led Away to Be Crucified",
      "Matthew": "27:32",
      "Mark": "15:21",
      "Luke": "23:26",
      "John": "19:17"
    },
    {
      "num": 197,
      "Event/Topic": "Jesus Is Crucified",
      "Matthew": "27:33–44",
      "Mark": "15:22–32",
      "Luke": "23:27–43",
      "John": "19:18–27"
    },
    {
      "num": 198,
      "Event/Topic": "Jesus Dies",
      "Matthew": "27:45–56",
      "Mark": "15:33–41",
      "Luke": "23:44–49",
      "John": "19:28–30"
    },
    {
      "num": 199,
      "Event/Topic": "Jesus Is Buried",
      "Matthew": "27:57–61",
      "Mark": "15:42–47",
      "Luke": "23:50–56",
      "John": "19:31–42"
    },
    {
      "num": 200,
      "Event/Topic": "Guards Are Posted at the Tomb",
      "Matthew": "27:62–66",
      "Mark": "",
      "Luke": "",
      "John": ""
    },
    {
      "num": 201,
      "Event/Topic": "Jesus Rises from the Dead",
      "Matthew": "28:1–10",
      "Mark": "16:1–11",
      "Luke": "24:1–12",
      "John": "20:1–18"
    },
    {
      "num": 202,
      "Event/Topic": "Religious Leaders Bribe the Guards",
      "Matthew": "28:11–15",
      "Mark": "",
      "Luke": "",
      "John": ""
    },
    {
      "num": 203,
      "Event/Topic": "Jesus Appears to Two Followers",
      "Matthew": "",
      "Mark": "16:12–13",
      "Luke": "24:13–35",
      "John": ""
    },
    {
      "num": 204,
      "Event/Topic": "Jesus Appears to the Disciples in Jerusalem",
      "Matthew": "",
      "Mark": "16:14",
      "Luke": "24:36–43",
      "John": "20:19–23"
    },
    {
      "num": 205,
      "Event/Topic": "Jesus Appears to Thomas",
      "Matthew": "",
      "Mark": "",
      "Luke": "",
      "John": "20:24–29"
    },
    {
      "num": 206,
      "Event/Topic": "Jesus Appears to Seven Disciples",
      "Matthew": "",
      "Mark": "",
      "Luke": "",
      "John": "21:1–23"
    },
    {
      "num": 207,
      "Event/Topic": "Jesus Gives His Final Commission",
      "Matthew": "28:16–20",
      "Mark": "16:15–18",
      "Luke": "",
      "John": ""
    },
    {
      "num": 208,
      "Event/Topic": "Jesus Ascends into Heaven",
      "Matthew": "",
      "Mark": "16:19–20",
      "Luke": "24:50–53",
      "John": ""
    },
    {
      "num": 209,
      "Event/Topic": "The Prologue: John’s Gospel",
      "Matthew": "",
      "Mark": "",
      "Luke": "",
      "John": "1:1–18"
    }
  ]
}
